[{"__type__":"cc.SpriteFrame","content":{"name":"daoju-tuoxie3","texture":"8daDYIO7lO4aD5WjTELBJ4","rect":[0,0,233,260],"offset":[0,0],"originalSize":[233,260]}},{"__type__":"cc.SpriteFrame","content":{"name":"daoju-tuoxie1","texture":"fdm46AFMxK0JdE9QBvfxgG","rect":[0,0,99,159],"offset":[0,0],"originalSize":[99,159]}},[{"__type__":"cc.Prefab","_name":"tuoxie","data":{"__id__":1},"asyncLoadAssets":null},{"__type__":"cc.Node","_name":"daoju-tuoxie-donghua","_children":[{"__id__":2},{"__id__":3},{"__id__":4},{"__id__":5},{"__id__":6},{"__id__":7},{"__id__":8},{"__id__":9}],"_components":[{"__type__":"cc.Animation","node":{"__id__":1},"_defaultClip":{"__uuid__":"d7/BHBdLlEY6LDEfn0rGGH"},"_clips":[{"__uuid__":"d7/BHBdLlEY6LDEfn0rGGH"}]}],"_prefab":{"__type__":"cc.PrefabInfo","root":{"__id__":1},"asset":{"__uuid__":"4bWhy5s6xNRbEkf4J/tWcZ"},"fileId":"502d8NSI0hPN7qGacuTlMQL"}},{"__type__":"cc.Node","_name":"tuoxie-1","_parent":{"__id__":1},"_components":[{"__type__":"cc.Sprite","node":{"__id__":2},"_spriteFrame":{"__uuid__":"34+K4MJKpMK6/u7qY74IEo"}}],"_prefab":{"__type__":"cc.PrefabInfo","root":{"__id__":1},"asset":{"__uuid__":"4bWhy5s6xNRbEkf4J/tWcZ"},"fileId":"98ea1EGs2ZIUZahWbBsQNKw"},"_contentSize":{"__type__":"cc.Size","width":99,"height":159},"_position":{"__type__":"cc.Vec2","x":-49.8,"y":1.5}},{"__type__":"cc.Node","_name":"tuoxie-2","_parent":{"__id__":1},"_components":[{"__type__":"cc.Sprite","node":{"__id__":3},"_spriteFrame":{"__uuid__":"d2oba4i9BMc4q59uEziIYo"}}],"_prefab":{"__type__":"cc.PrefabInfo","root":{"__id__":1},"asset":{"__uuid__":"4bWhy5s6xNRbEkf4J/tWcZ"},"fileId":"52a68bM1ipIA75FhNBZlAGX"},"_contentSize":{"__type__":"cc.Size","width":83,"height":165},"_position":{"__type__":"cc.Vec2","x":24.5,"y":-3.8}},{"__type__":"cc.Node","_name":"tuoxie-5","_parent":{"__id__":1},"_components":[{"__type__":"cc.Sprite","node":{"__id__":4},"_spriteFrame":{"__uuid__":"02gWT5GOhPJpkcqyNKDFms"}}],"_prefab":{"__type__":"cc.PrefabInfo","root":{"__id__":1},"asset":{"__uuid__":"4bWhy5s6xNRbEkf4J/tWcZ"},"fileId":"502d04L36NMPYVVtAVUKIom"},"_contentSize":{"__type__":"cc.Size","width":233,"height":260},"_scaleX":0.8,"_scaleY":0.8,"_position":{"__type__":"cc.Vec2","x":22,"y":31.3}},{"__type__":"cc.Node","_name":"tuoxie-6","_parent":{"__id__":1},"_components":[{"__type__":"cc.Sprite","node":{"__id__":5},"_spriteFrame":{"__uuid__":"02gWT5GOhPJpkcqyNKDFms"}}],"_prefab":{"__type__":"cc.PrefabInfo","root":{"__id__":1},"asset":{"__uuid__":"4bWhy5s6xNRbEkf4J/tWcZ"},"fileId":"bc45aat/EBExK04kAEE5L4M"},"_contentSize":{"__type__":"cc.Size","width":233,"height":260},"_scaleX":0.8,"_scaleY":0.8,"_position":{"__type__":"cc.Vec2","x":-67.7,"y":39.7}},{"__type__":"cc.Node","_name":"tuoxie-3","_parent":{"__id__":1},"_components":[{"__type__":"cc.Sprite","node":{"__id__":6},"_spriteFrame":{"__uuid__":"a0/olag4FD3ZTKTspdZd4G"}}],"_prefab":{"__type__":"cc.PrefabInfo","root":{"__id__":1},"asset":{"__uuid__":"4bWhy5s6xNRbEkf4J/tWcZ"},"fileId":"21b1bOn3eBEm5WEr2MFZlTA"},"_contentSize":{"__type__":"cc.Size","width":37,"height":37},"_position":{"__type__":"cc.Vec2","x":22.3,"y":35}},{"__type__":"cc.Node","_name":"tuoxie-4","_parent":{"__id__":1},"_components":[{"__type__":"cc.Sprite","node":{"__id__":7},"_spriteFrame":{"__uuid__":"a0/olag4FD3ZTKTspdZd4G"}}],"_prefab":{"__type__":"cc.PrefabInfo","root":{"__id__":1},"asset":{"__uuid__":"4bWhy5s6xNRbEkf4J/tWcZ"},"fileId":"ca851VbDRpPDaFz7Bc/25He"},"_contentSize":{"__type__":"cc.Size","width":37,"height":37},"_position":{"__type__":"cc.Vec2","x":-49.4,"y":35}},{"__type__":"cc.Node","_name":"tuoxie-0","_parent":{"__id__":1},"_components":[{"__type__":"cc.Sprite","node":{"__id__":8},"_spriteFrame":{"__uuid__":"deCi1UpC5Ls5HXLwlJk3TN"}}],"_prefab":{"__type__":"cc.PrefabInfo","root":{"__id__":1},"asset":{"__uuid__":"4bWhy5s6xNRbEkf4J/tWcZ"},"fileId":"7bb727svXFK+oLn7VY6/O78"},"_contentSize":{"__type__":"cc.Size","width":120,"height":133},"_rotationX":15,"_rotationY":15,"_position":{"__type__":"cc.Vec2","x":-48.8,"y":7}},{"__type__":"cc.Node","_name":"tuoxie-7","_parent":{"__id__":1},"_components":[{"__type__":"cc.Sprite","node":{"__id__":9},"_spriteFrame":{"__uuid__":"deCi1UpC5Ls5HXLwlJk3TN"}}],"_prefab":{"__type__":"cc.PrefabInfo","root":{"__id__":1},"asset":{"__uuid__":"4bWhy5s6xNRbEkf4J/tWcZ"},"fileId":"6dae4yoLlFLRK0HRWzcJQ4g"},"_contentSize":{"__type__":"cc.Size","width":120,"height":133},"_rotationX":53.20000000000008,"_rotationY":53.20000000000008,"_position":{"__type__":"cc.Vec2","x":12.3,"y":-3}}],{"__type__":"cc.SpriteFrame","content":{"name":"daoju-tuoxie4","texture":"1638nM4SpE17EOYIYCIdA2","rect":[0,0,37,37],"offset":[0,0],"originalSize":[37,37]}},{"__type__":"cc.SpriteFrame","content":{"name":"daoju-tuoxie2","texture":"05O68zV4ZPRJyHC0uPqXY8","rect":[0,0,83,165],"offset":[0,0],"originalSize":[83,165]}},{"__type__":"cc.AnimationClip","_name":"daoju-tuoxie-donghua","_duration":2,"curveData":{"paths":{"tuoxie-0":{"props":{"scaleX":[{"frame":0,"value":2},{"frame":0.08333333333333333,"value":1},{"frame":0.13333333333333333,"value":0.9},{"frame":0.18333333333333332,"value":1}],"scaleY":[{"frame":0,"value":2},{"frame":0.08333333333333333,"value":1},{"frame":0.13333333333333333,"value":0.9},{"frame":0.18333333333333332,"value":1}],"opacity":[{"frame":0,"value":0},{"frame":0.08333333333333333,"value":255},{"frame":0.23333333333333334,"value":255},{"frame":0.2833333333333333,"value":0}]}},"tuoxie-6":{"props":{"scaleX":[{"frame":0.08333333333333333,"value":0},{"frame":0.15,"value":0.8},{"frame":0.21666666666666667,"value":1}],"scaleY":[{"frame":0.08333333333333333,"value":0},{"frame":0.15,"value":0.8},{"frame":0.21666666666666667,"value":1}],"opacity":[{"frame":0.08333333333333333,"value":0},{"frame":0.15,"value":255},{"frame":0.21666666666666667,"value":0}]}},"tuoxie-1":{"props":{"opacity":[{"frame":0.13333333333333333,"value":0},{"frame":0.2,"value":255},{"frame":1.9166666666666667,"value":255},{"frame":2,"value":0}]}},"tuoxie-7":{"props":{"scaleX":[{"frame":0.38333333333333336,"value":2},{"frame":0.4666666666666667,"value":1},{"frame":0.5166666666666667,"value":0.9},{"frame":0.5666666666666667,"value":1}],"scaleY":[{"frame":0.38333333333333336,"value":2},{"frame":0.4666666666666667,"value":1},{"frame":0.5166666666666667,"value":0.9},{"frame":0.5666666666666667,"value":1}],"opacity":[{"frame":0.38333333333333336,"value":0},{"frame":0.4666666666666667,"value":255},{"frame":0.6166666666666667,"value":255},{"frame":0.6666666666666666,"value":0}]}},"tuoxie-3":{"props":{"scaleX":[{"frame":0.6666666666666666,"value":1},{"frame":0.75,"value":1},{"frame":0.8333333333333334,"value":1},{"frame":1.2666666666666666,"value":1}],"scaleY":[{"frame":0.6666666666666666,"value":0},{"frame":0.75,"value":1.1},{"frame":0.8333333333333334,"value":1},{"frame":1.2666666666666666,"value":1},{"frame":1.3333333333333333,"value":0},{"frame":1.4,"value":1},{"frame":1.5333333333333334,"value":1},{"frame":1.6,"value":0},{"frame":1.6666666666666667,"value":1}],"opacity":[{"frame":0.6666666666666666,"value":0},{"frame":0.75,"value":255},{"frame":1.8833333333333333,"value":255},{"frame":2,"value":0}]}},"tuoxie-2":{"props":{"opacity":[{"frame":0.5166666666666667,"value":0},{"frame":0.5833333333333334,"value":255},{"frame":1.9166666666666667,"value":255},{"frame":2,"value":0}]}},"tuoxie-5":{"props":{"scaleX":[{"frame":0.4666666666666667,"value":0},{"frame":0.5333333333333333,"value":0.8},{"frame":0.6,"value":1}],"scaleY":[{"frame":0.4666666666666667,"value":0},{"frame":0.5333333333333333,"value":0.8},{"frame":0.6,"value":1}],"opacity":[{"frame":0.4666666666666667,"value":0},{"frame":0.5333333333333333,"value":255},{"frame":0.6,"value":0}]}},"tuoxie-4":{"props":{"scaleX":[{"frame":0.6666666666666666,"value":1},{"frame":0.75,"value":1},{"frame":0.8333333333333334,"value":1}],"scaleY":[{"frame":0.6666666666666666,"value":0},{"frame":0.75,"value":1.1},{"frame":0.8333333333333334,"value":1},{"frame":1.2666666666666666,"value":1},{"frame":1.3333333333333333,"value":0},{"frame":1.4,"value":1},{"frame":1.5333333333333334,"value":1},{"frame":1.6,"value":0},{"frame":1.6666666666666667,"value":1}],"opacity":[{"frame":0.6666666666666666,"value":0},{"frame":0.75,"value":255},{"frame":1.8833333333333333,"value":255},{"frame":2,"value":0}]}}}}},{"__type__":"cc.SpriteFrame","content":{"name":"daoju-tuoxie0","texture":"6fh+TV59lAUrj3R4gO3gSA","rect":[0,0,120,133],"offset":[0,0],"originalSize":[120,133]}}]